pf_py_common/__init__.py
pf_py_common/pf_exception.py
pf_py_common/py_common.py
pf_py_common/py_data_util.py
PF_PY_Common-1.0.2.dist-info/LICENSE
PF_PY_Common-1.0.2.dist-info/METADATA
PF_PY_Common-1.0.2.dist-info/WHEEL
PF_PY_Common-1.0.2.dist-info/top_level.txt
PF_PY_Common-1.0.2.dist-info/RECORD
