Metadata-Version: 2.1
Name: PF-PY-Common
Version: 1.0.2
Summary: Python Common things by Problem Fighter Library, (Exception, Debug Log, etc.)
Home-page: https://github.com/problemfighter/pf-py-common
Author: Problem Fighter
Author-email: problemfighter.com@gmail.com
License: Apache 2.0
Platform: any
Classifier: Intended Audience :: Developers
Classifier: License :: OSI Approved :: Apache Software License
Classifier: Programming Language :: Python
